{
  "id": "01",
  "userid": "dhivya_dhurai",
  "list": [
    {
      "id": 0,
      "url": "FiEmPJOacAAT07W"
    },
    {
      "id": 1,
      "url": "FiEmS1FaYAA4d0f"
    },
    {
      "id": 2,
      "url": "FiEmYk-aAAIzRe7"
    },
    {
      "id": 3,
      "url": "FiEmuicaMAA_QfS"
    },
    {
      "id": 4,
      "url": "FiDchlCaYAMpxVt"
    },
    {
      "id": 5,
      "url": "Fh7DkgvagAAfFRr"
    },
    {
      "id": 6,
      "url": "Fh7DlqXaUAAaCuc"
    },
    {
      "id": 7,
      "url": "Fh7DmhbaYAAByG4"
    },
    {
      "id": 8,
      "url": "Fh7DniyacAIKOCO"
    },
    {
      "id": 9,
      "url": "Fh06VUkaMAA4RUt"
    },
    {
      "id": 10,
      "url": "Fh06WT8akAAV0kP"
    },
    {
      "id": 11,
      "url": "Fh06XZzagAAetE9"
    },
    {
      "id": 12,
      "url": "Fh06YUOaMAE5cYO"
    },
    {
      "id": 13,
      "url": "FhC1c5haMAADiGl"
    },
    {
      "id": 14,
      "url": "FgaTRMgakAAG9dG"
    },
    {
      "id": 15,
      "url": "FfzuNUgacAAf2II"
    },
    {
      "id": 16,
      "url": "FfzuOZ6aUAAF0sS"
    },
    {
      "id": 17,
      "url": "FflvLL9acAEfCij"
    },
    {
      "id": 18,
      "url": "FflvMheacAM6T7L"
    },
    {
      "id": 19,
      "url": "FflvObqaAAAb8ft"
    },
    {
      "id": 20,
      "url": "FflvP42agAAEOWq"
    },
    {
      "id": 21,
      "url": "FfVq--QaAAESArt"
    },
    {
      "id": 22,
      "url": "FfMq-5GacAEEaew"
    },
    {
      "id": 23,
      "url": "FfMq_5SaAAAse1b"
    },
    {
      "id": 24,
      "url": "FfMrAqNagAASZPQ"
    },
    {
      "id": 25,
      "url": "FfMrBcEaUAAIMfd"
    },
    {
      "id": 26,
      "url": "Fe84c_baEAErPYP"
    },
    {
      "id": 27,
      "url": "Fe84dmIaMAIjejx"
    },
    {
      "id": 28,
      "url": "Fez_P9EaUAAWYHg"
    },
    {
      "id": 29,
      "url": "FdLnaqnaAAAnk32"
    },
    {
      "id": 30,
      "url": "Fc1jIhHaEAMuMOb"
    },
    {
      "id": 31,
      "url": "Fcc-ShaaAAAFJtr"
    },
    {
      "id": 32,
      "url": "FcCvmjIacAA8aTL"
    },
    {
      "id": 33,
      "url": "FabfG03aIAAMmsY"
    },
    {
      "id": 34,
      "url": "FaWnbqDaAAAxy5S"
    },
    {
      "id": 35,
      "url": "FaModwHaMAECJpJ"
    },
    {
      "id": 36,
      "url": "FaMoe2AaIAAU4Uu"
    },
    {
      "id": 37,
      "url": "FZeaR1EaAAEJKYJ"
    },
    {
      "id": 38,
      "url": "FY1Q7B0aUAI1BQn"
    },
    {
      "id": 39,
      "url": "FY1Q8BoaAAE9bKn"
    },
    {
      "id": 40,
      "url": "FYrAv_jakAEh78z"
    },
    {
      "id": 41,
      "url": "FYrAxIEaMAIFhBJ"
    },
    {
      "id": 42,
      "url": "FYrAyIdagAA3n9D"
    },
    {
      "id": 43,
      "url": "FYrAzPHaIAAA0Rs"
    },
    {
      "id": 44,
      "url": "FYRHBbXacAAWzMR"
    },
    {
      "id": 45,
      "url": "FYG8HOPaUAEt56r"
    },
    {
      "id": 46,
      "url": "FYG8H4uaAAY2hac"
    },
    {
      "id": 47,
      "url": "FYG8IhrakAEW3Sg"
    },
    {
      "id": 48,
      "url": "FYG8JH9agAUKnkz"
    },
    {
      "id": 49,
      "url": "FX3VsrtaUAIhI8Q"
    },
    {
      "id": 50,
      "url": "FX3Vti6agAAmI7D"
    },
    {
      "id": 51,
      "url": "FX3VuTlaIAElpO8"
    },
    {
      "id": 52,
      "url": "FX3VvFHaMAE75wr"
    },
    {
      "id": 53,
      "url": "FXrqXcqaMAAOPXK"
    },
    {
      "id": 54,
      "url": "FXiz6JYaUAEaRxU"
    },
    {
      "id": 55,
      "url": "FXiz7EaacAAS85b"
    },
    {
      "id": 56,
      "url": "FXiz765aIAAjDTi"
    },
    {
      "id": 57,
      "url": "FXiz9GHakAAFr1e"
    },
    {
      "id": 58,
      "url": "FWVo1ViagAAeDQ9"
    },
    {
      "id": 59,
      "url": "FWP63yfaQAUjN1A"
    },
    {
      "id": 60,
      "url": "FWP64RfaUAAfUPI"
    },
    {
      "id": 61,
      "url": "FWNLQ9NacAA7oKZ"
    },
    {
      "id": 62,
      "url": "FWGGoiwaAAAnqwN"
    },
    {
      "id": 63,
      "url": "FWGGpmTagAM0w1w"
    },
    {
      "id": 64,
      "url": "FWGGqv1aQAAyjXj"
    },
    {
      "id": 65,
      "url": "FWGGrzqaQAE_B7A"
    },
    {
      "id": 66,
      "url": "FV75lcoaMAAaDYm"
    },
    {
      "id": 67,
      "url": "FV75mmvaMAE03vM"
    },
    {
      "id": 68,
      "url": "FV75nrcaMAASZAi"
    },
    {
      "id": 69,
      "url": "FV75ow0aIAEYkvm"
    },
    {
      "id": 70,
      "url": "FVc6kycXwAAyv0v"
    },
    {
      "id": 71,
      "url": "FVc6laeX0AEu6eb"
    },
    {
      "id": 72,
      "url": "FVc6mAXXEAIHJg6"
    },
    {
      "id": 73,
      "url": "FVc6mb1WIAExPY7"
    },
    {
      "id": 74,
      "url": "FVSsBPgXsAAZllV"
    },
    {
      "id": 75,
      "url": "FVSsB1tWQAIoxJk"
    },
    {
      "id": 76,
      "url": "FVIcdcsXsAQK7Hg"
    },
    {
      "id": 77,
      "url": "FVIceoTXoAAc1l5"
    },
    {
      "id": 78,
      "url": "FVH8uNMWUAUvHOn"
    },
    {
      "id": 79,
      "url": "FVH8u9-WYAEynC1"
    },
    {
      "id": 80,
      "url": "FVH8viGWIAIS98S"
    },
    {
      "id": 81,
      "url": "FU-Gn9NX0AA-Jwa"
    },
    {
      "id": 82,
      "url": "FU-GpI3WAAgvM-P"
    },
    {
      "id": 83,
      "url": "FU9U1lHWIAAaus3"
    },
    {
      "id": 84,
      "url": "FU4kRxDWAAEl7li"
    },
    {
      "id": 85,
      "url": "FUy5h6NagAANFL6"
    },
    {
      "id": 86,
      "url": "FUupMV0WUAEhcEw"
    },
    {
      "id": 87,
      "url": "FUupNipXwAEBDzW"
    },
    {
      "id": 88,
      "url": "FUpdLA6XwAA1e-H"
    },
    {
      "id": 89,
      "url": "FUpdMJZWAAE5wmz"
    },
    {
      "id": 90,
      "url": "FUnwM-3aIAEnn8P"
    },
    {
      "id": 91,
      "url": "FUPrylNaMAAu441"
    },
    {
      "id": 92,
      "url": "FULNiSYakAAdKnO"
    },
    {
      "id": 93,
      "url": "FULNjbbaUAEhf3l"
    },
    {
      "id": 94,
      "url": "FUFbJw2akAEKJ45"
    },
    {
      "id": 95,
      "url": "FUFbK0iaMAAV0Rn"
    },
    {
      "id": 96,
      "url": "FT19QOGWAAA8AkV"
    },
    {
      "id": 97,
      "url": "FT19RaOXwAALwUs"
    },
    {
      "id": 98,
      "url": "FT19SmMX0AABiPY"
    },
    {
      "id": 99,
      "url": "FT19TsVWAAMcjB_"
    },
    {
      "id": 100,
      "url": "FTrXxl5WAAEmdtx"
    },
    {
      "id": 101,
      "url": "FTrXy_BX0AIA9E0"
    },
    {
      "id": 102,
      "url": "FTrX0LtWYAEeD3_"
    },
    {
      "id": 103,
      "url": "FTrX1fqWAAABWjP"
    },
    {
      "id": 104,
      "url": "FTmcVd9aQAA_S7b"
    },
    {
      "id": 105,
      "url": "FTmcZnkaMAA5Lp8"
    },
    {
      "id": 106,
      "url": "FTmcd5LagAIxCGC"
    },
    {
      "id": 107,
      "url": "FTmcj7FaAAE6tGL"
    },
    {
      "id": 108,
      "url": "FTBpA6eWIAA8vh3"
    },
    {
      "id": 109,
      "url": "FRyxvI9aMAAjsp6"
    },
    {
      "id": 110,
      "url": "FRMbArzaMAEsD21"
    },
    {
      "id": 111,
      "url": "FQ8ic8NXMAI3vJX"
    },
    {
      "id": 112,
      "url": "FQ8C8ehagAE7zlw"
    },
    {
      "id": 113,
      "url": "FQy7CG3aQAELKnL"
    },
    {
      "id": 114,
      "url": "FQtH8hBaUAEBqSm"
    },
    {
      "id": 115,
      "url": "FQtH9HtaIAMZp1V"
    },
    {
      "id": 116,
      "url": "FQtH9xnaMAUEGte"
    },
    {
      "id": 117,
      "url": "FQtH-yUaIBUI1y5"
    },
    {
      "id": 118,
      "url": "FQmRzeNX0AUEFGr"
    },
    {
      "id": 119,
      "url": "FQh627faIAgxvTR"
    },
    {
      "id": 120,
      "url": "FQh64VdaMAAPVt6"
    },
    {
      "id": 121,
      "url": "FQet1LSaIAQFXB1"
    },
    {
      "id": 122,
      "url": "FQdnns_aUAEgQDL"
    },
    {
      "id": 123,
      "url": "FQYX2YoWUAQG4Cw"
    },
    {
      "id": 124,
      "url": "FQYX3lbXIA8FGNg"
    },
    {
      "id": 125,
      "url": "FQYX4tpWUAUvLjB"
    },
    {
      "id": 126,
      "url": "FQYX5yzXEAEmMfU"
    },
    {
      "id": 127,
      "url": "FQRzFlJacAUZBgZ"
    },
    {
      "id": 128,
      "url": "FQRqhjZaIAI1Lxc"
    },
    {
      "id": 129,
      "url": "FQRqiLzaMAYNbgc"
    },
    {
      "id": 130,
      "url": "FQMvfQJagAIjbju"
    },
    {
      "id": 131,
      "url": "FQELAFyaMAEB6cd"
    },
    {
      "id": 132,
      "url": "FP96RAqacAQUQ7o"
    },
    {
      "id": 133,
      "url": "FP6J5BJXwAMzIw9"
    },
    {
      "id": 134,
      "url": "FP6B6-9aAAIXQFY"
    },
    {
      "id": 135,
      "url": "FP5hLAUaUAE7wLM"
    },
    {
      "id": 136,
      "url": "FP0j1cRaQAMvj87"
    },
    {
      "id": 137,
      "url": "FP0dfFbaQAgao1f"
    },
    {
      "id": 138,
      "url": "FP0Z0MxaQAUVEUG"
    },
    {
      "id": 139,
      "url": "FP0OQnkakAgVFOG"
    },
    {
      "id": 140,
      "url": "FPy_AaRVIAQs2Ko"
    },
    {
      "id": 141,
      "url": "FPrIsfsaQAM_PqO"
    },
    {
      "id": 142,
      "url": "FPo4D-uaAAA1T98"
    },
    {
      "id": 143,
      "url": "FPo4EqMacAIA78L"
    },
    {
      "id": 144,
      "url": "FPo4E5DaMAIyYjp"
    },
    {
      "id": 145,
      "url": "FPo4GFeacAUdy2G"
    },
    {
      "id": 146,
      "url": "FPmOJhHacAArbYI"
    },
    {
      "id": 147,
      "url": "FPmOKNXakAEXh6G"
    },
    {
      "id": 148,
      "url": "FPUB39YaIAALZbj"
    },
    {
      "id": 149,
      "url": "FPCb60-akAAooWw"
    },
    {
      "id": 150,
      "url": "FOZMi7xacAAa-qa"
    },
    {
      "id": 151,
      "url": "FOMzGrTakAYpzq8"
    },
    {
      "id": 152,
      "url": "FOMzHL-agAEpjlW"
    },
    {
      "id": 153,
      "url": "FOMzHq3agAE9SMP"
    },
    {
      "id": 154,
      "url": "FOMzIHzaQAEHrc5"
    },
    {
      "id": 155,
      "url": "FN-VWbLaQAYNb7z"
    },
    {
      "id": 156,
      "url": "FNy4e2TaQAM5yv_"
    },
    {
      "id": 157,
      "url": "FNv2lM3aQAELYm4"
    },
    {
      "id": 158,
      "url": "FNu2aOlaUA8RLlN"
    },
    {
      "id": 159,
      "url": "FNklJ9NaAAEjCpU"
    },
    {
      "id": 160,
      "url": "FNklMnJaIAE2hIL"
    },
    {
      "id": 161,
      "url": "FNklPiPaQAc_t0n"
    },
    {
      "id": 162,
      "url": "FNklS0xaQAIQsgH"
    },
    {
      "id": 163,
      "url": "FNfwo--aIAkuPgd"
    },
    {
      "id": 164,
      "url": "FNS_h5sacAMKL8S"
    },
    {
      "id": 165,
      "url": "FNIpgbOagAAN0DD"
    },
    {
      "id": 166,
      "url": "FNAkGjjaAAMoZEE"
    },
    {
      "id": 167,
      "url": "FNAkH7CagAEH0YS"
    },
    {
      "id": 168,
      "url": "FNAkB_pagAAn0oF"
    },
    {
      "id": 169,
      "url": "FNAkDPuagAEBGEH"
    },
    {
      "id": 170,
      "url": "FMrijd3aUAMn9pQ"
    },
    {
      "id": 171,
      "url": "FMrikf0agAggTc0"
    },
    {
      "id": 172,
      "url": "FMq05icaUAIy1JH"
    },
    {
      "id": 173,
      "url": "FMg2iNaaAAYyPsz"
    },
    {
      "id": 174,
      "url": "FMWcNg3aIAok-Rq"
    },
    {
      "id": 175,
      "url": "FMLoU_oaAAICRHl"
    },
    {
      "id": 176,
      "url": "FMB4P52aUAQpIPo"
    },
    {
      "id": 177,
      "url": "FLsmna5akAIhObz"
    },
    {
      "id": 178,
      "url": "FLPOQ_SaIAAIbGY"
    },
    {
      "id": 179,
      "url": "FKsL696aMAIxslU"
    },
    {
      "id": 180,
      "url": "FJdiXR0acAIGVPW"
    },
    {
      "id": 181,
      "url": "FJdiXv0aUAkHJJ5"
    },
    {
      "id": 182,
      "url": "FJYbdzTaMAA1zzz"
    },
    {
      "id": 183,
      "url": "FJYbei9aUAQVN0a"
    },
    {
      "id": 184,
      "url": "FJD0TUQaAAEWGZN"
    },
    {
      "id": 185,
      "url": "FJD0T7ZaMAIxRt3"
    },
    {
      "id": 186,
      "url": "FJD0UhGaMAE9QiL"
    },
    {
      "id": 187,
      "url": "FJD0VJAagAElnZs"
    },
    {
      "id": 188,
      "url": "FJCWT2jaAAI4rj8"
    },
    {
      "id": 189,
      "url": "FJCWVOFaUAA56dl"
    },
    {
      "id": 190,
      "url": "FJCWWk5akAAbUP4"
    },
    {
      "id": 191,
      "url": "FJCWXwVaUAAVDyP"
    },
    {
      "id": 192,
      "url": "FIueCV-VkAM72Ii"
    },
    {
      "id": 193,
      "url": "FIueCtOUcAIZnlR"
    },
    {
      "id": 194,
      "url": "FIuc69LVgAEFzgN"
    },
    {
      "id": 195,
      "url": "FIk8ZHUVEAkr4G4"
    },
    {
      "id": 196,
      "url": "FIk8aWCVEAEbGx5"
    },
    {
      "id": 197,
      "url": "FIk8bwWVIAA3yg-"
    },
    {
      "id": 198,
      "url": "FIk8dTjVIAENDnY"
    },
    {
      "id": 199,
      "url": "FIWgIzjUUAAKRpv"
    },
    {
      "id": 200,
      "url": "FIWgJp3UUAE8qIg"
    },
    {
      "id": 201,
      "url": "FIWgKoRVgAAhiuu"
    },
    {
      "id": 202,
      "url": "FIWgLsBVkAEx9jt"
    },
    {
      "id": 203,
      "url": "FIVo5hjVkAI_Z02"
    },
    {
      "id": 204,
      "url": "FIVo6ngUcAEZwqY"
    },
    {
      "id": 205,
      "url": "FIVo75NUUAAuLFP"
    },
    {
      "id": 206,
      "url": "FH9R1RvVQAUnk-N"
    },
    {
      "id": 207,
      "url": "FH9R2eeVQAEElDN"
    },
    {
      "id": 208,
      "url": "FH9R3udVUAEuV-h"
    },
    {
      "id": 209,
      "url": "FH9R4i9VkAAHvxZ"
    },
    {
      "id": 210,
      "url": "FH2jpmeVUAEZoJF"
    },
    {
      "id": 211,
      "url": "FH2jrCSVUAI0iMG"
    },
    {
      "id": 212,
      "url": "FH2jshIUUAMMqez"
    },
    {
      "id": 213,
      "url": "FHx68vZUUAEehjT"
    },
    {
      "id": 214,
      "url": "FHboN0NVEAAL6xT"
    },
    {
      "id": 215,
      "url": "FGgfrH-UUAIOhLt"
    },
    {
      "id": 216,
      "url": "FGYWnYnVUAEAPco"
    },
    {
      "id": 217,
      "url": "FGKkg5mVQAYf9gx"
    },
    {
      "id": 218,
      "url": "FGKkha3VIAEZ1XU"
    },
    {
      "id": 219,
      "url": "FGD3VvdVcAEiFNc"
    },
    {
      "id": 220,
      "url": "FF7Ez1gVQAAiWyb"
    },
    {
      "id": 221,
      "url": "FF7E0GuVIAMvZyE"
    },
    {
      "id": 222,
      "url": "FEehYakUcAEvgDG"
    },
    {
      "id": 223,
      "url": "FD0058aVEAAV7RU"
    },
    {
      "id": 224,
      "url": "FDkI_pGVIAQvEN2"
    },
    {
      "id": 225,
      "url": "FDLASIbVUAYLZVQ"
    },
    {
      "id": 226,
      "url": "FDKegMMUcAcgQPm"
    },
    {
      "id": 227,
      "url": "FDB3AGDVgAsqtOE"
    },
    {
      "id": 228,
      "url": "FDB3Av0VEBEA4vw"
    },
    {
      "id": 229,
      "url": "FC8iiwlUUAcDMVh"
    },
    {
      "id": 230,
      "url": "FC2xkK6VIAout8f"
    },
    {
      "id": 231,
      "url": "FCwjAzzVEAAbnSH"
    },
    {
      "id": 232,
      "url": "FCrTWzKVQAUiRuO"
    },
    {
      "id": 233,
      "url": "FCrTXV8VQAUwsaZ"
    },
    {
      "id": 234,
      "url": "FCTYGNpVkAoQsJr"
    },
    {
      "id": 235,
      "url": "FCTYHGmVQAEg7va"
    },
    {
      "id": 236,
      "url": "FCTYH_BVcAsTHKT"
    },
    {
      "id": 237,
      "url": "FCTYI1GVcAA9gDh"
    },
    {
      "id": 238,
      "url": "FCJFjPAVEAM77vF"
    },
    {
      "id": 239,
      "url": "FCJFj-4UcAMkBjo"
    },
    {
      "id": 240,
      "url": "FCJFk24VgAYiDI2"
    },
    {
      "id": 241,
      "url": "FCJFly6UcAIrEuZ"
    },
    {
      "id": 242,
      "url": "FBVXw74UUAIOxjk"
    },
    {
      "id": 243,
      "url": "E-5vuVKVEAE9FtK"
    },
    {
      "id": 244,
      "url": "E-Xz4tRVUAEEcRh"
    },
    {
      "id": 245,
      "url": "E-LNo1aVkAcibUE"
    },
    {
      "id": 246,
      "url": "E-LNptwVUAEay1X"
    },
    {
      "id": 247,
      "url": "E-LNqhOUcAEGw8J"
    },
    {
      "id": 248,
      "url": "E89RKOhVIAMIEuN"
    },
    {
      "id": 249,
      "url": "E8lA32nVIAMjrUJ"
    },
    {
      "id": 250,
      "url": "E7_6MGGUUAA18C-"
    },
    {
      "id": 251,
      "url": "E7Hln1gXIAUgiE_"
    },
    {
      "id": 252,
      "url": "E7CWarRWUAAmy30"
    },
    {
      "id": 253,
      "url": "E7CWcLlWEAAZO4Q"
    },
    {
      "id": 254,
      "url": "E6_u011VIAQ5Ilp"
    },
    {
      "id": 255,
      "url": "E6_u1aVVUAYDQYN"
    },
    {
      "id": 256,
      "url": "E6wY60GUUAIDAZt"
    },
    {
      "id": 257,
      "url": "E6qJYgPUUAQmvWU"
    },
    {
      "id": 258,
      "url": "E6qJZjcVoAIrfy7"
    },
    {
      "id": 259,
      "url": "E6a1xIlVEAIWQFZ"
    },
    {
      "id": 260,
      "url": "E6V_f7YVcBI2uAV"
    },
    {
      "id": 261,
      "url": "E6LDPR7UUAATSuS"
    },
    {
      "id": 262,
      "url": "E6LDQwZVgAMD6Na"
    },
    {
      "id": 263,
      "url": "E6LDSPwUYAQlvvJ"
    },
    {
      "id": 264,
      "url": "E6LDToIVcAMfto_"
    },
    {
      "id": 265,
      "url": "E5XziWuUUAAy3xL"
    },
    {
      "id": 266,
      "url": "E5Xzi_9VoAYe5gW"
    },
    {
      "id": 267,
      "url": "E5Xzjc5VEAEWC67"
    },
    {
      "id": 268,
      "url": "E5Xzj_8VUAEUFwv"
    },
    {
      "id": 269,
      "url": "E4aAjgbVEAM8Owp"
    },
    {
      "id": 270,
      "url": "E4FND5TUUAQlWvD"
    },
    {
      "id": 271,
      "url": "E4FNE80VkAUgX5s"
    },
    {
      "id": 272,
      "url": "E3vqzGFVgAQ9LdK"
    },
    {
      "id": 273,
      "url": "E3LbduMUYAQx24Q"
    },
    {
      "id": 274,
      "url": "E2jEXf7UcAQys08"
    },
    {
      "id": 275,
      "url": "E2PeJTLXMAwS6io"
    },
    {
      "id": 276,
      "url": "E2PeKXFXEAc0P0M"
    },
    {
      "id": 277,
      "url": "E2KCmkjVEAAf0kr"
    },
    {
      "id": 278,
      "url": "E1_WmGIXsAMIdhY"
    },
    {
      "id": 279,
      "url": "E15ddPZXMAEpJjc"
    },
    {
      "id": 280,
      "url": "E1wgoCpVgAAg03q"
    },
    {
      "id": 281,
      "url": "E1wgpaxUUAgDeLo"
    },
    {
      "id": 282,
      "url": "E1wgYUNVcAAbOXx"
    },
    {
      "id": 283,
      "url": "E1wgZVaVgAc4ek-"
    },
    {
      "id": 284,
      "url": "E1j9MTaXoAgA42B"
    },
    {
      "id": 285,
      "url": "E1hPTF4VIAQbexw"
    },
    {
      "id": 286,
      "url": "E1UHtp5UUAAWCKh"
    },
    {
      "id": 287,
      "url": "E03Mj_RUUAAJjBE"
    },
    {
      "id": 288,
      "url": "E03MkxsVUAYfK-L"
    },
    {
      "id": 289,
      "url": "E03MlmVUcAYuSGv"
    },
    {
      "id": 290,
      "url": "E03MmVkVgAQu8ph"
    },
    {
      "id": 291,
      "url": "E0yCrrdVUAIE_Dt"
    },
    {
      "id": 292,
      "url": "E0yCtOVVgAEnkx3"
    },
    {
      "id": 293,
      "url": "E0yCuzqVkAI6JPD"
    },
    {
      "id": 294,
      "url": "E0yCwEzVUAMIVSe"
    },
    {
      "id": 295,
      "url": "E0s5F1xVgAQ9fd_"
    },
    {
      "id": 296,
      "url": "E0s5G5bVEAYXCOc"
    },
    {
      "id": 297,
      "url": "E0jwklzVgAALZNp"
    },
    {
      "id": 298,
      "url": "E0YM-lXVcAAJ0wQ"
    },
    {
      "id": 299,
      "url": "E0XzJ1jVUAQlAzF"
    },
    {
      "id": 300,
      "url": "E0XSH_0VIAEc9hR"
    },
    {
      "id": 301,
      "url": "E0IhC-vVIAEh2Vt"
    },
    {
      "id": 302,
      "url": "Ez9KCD1UcAEUo0Z"
    },
    {
      "id": 303,
      "url": "Ez0OQ6AWQAAOe3a"
    },
    {
      "id": 304,
      "url": "EzreLBhUUAggCC4"
    },
    {
      "id": 305,
      "url": "EzqO_8vVUAMAnD5"
    },
    {
      "id": 306,
      "url": "EzoIRtgVgAMmqpj"
    },
    {
      "id": 307,
      "url": "Ezl7aPUVoAMrXwq"
    },
    {
      "id": 308,
      "url": "EzgkiqsVcAADxZw"
    },
    {
      "id": 309,
      "url": "EzJF4ueVcAEHvu7"
    },
    {
      "id": 310,
      "url": "EzGxJWLUYAQNQ2n"
    },
    {
      "id": 311,
      "url": "EzFCpYXVgAkTwq-"
    },
    {
      "id": 312,
      "url": "Ey_8YrFVkAI0tOt"
    },
    {
      "id": 313,
      "url": "Ey_8ZKpVIAAS1HE"
    },
    {
      "id": 314,
      "url": "Ey_8ZjWVgAE_Tqb"
    },
    {
      "id": 315,
      "url": "Ey_8aB8UcAI7XT_"
    },
    {
      "id": 316,
      "url": "Ey6JUSBXIAA-uVG"
    },
    {
      "id": 317,
      "url": "Ey6JZfuXIAEV9qX"
    },
    {
      "id": 318,
      "url": "Ey6JceLXEAAEUMd"
    },
    {
      "id": 319,
      "url": "Ey20vNjUUAcfPum"
    },
    {
      "id": 320,
      "url": "Eyq1ytZUcAM5ama"
    },
    {
      "id": 321,
      "url": "EygznnhUcAEd80w"
    },
    {
      "id": 322,
      "url": "EybT1_rVEAAAQ1N"
    },
    {
      "id": 323,
      "url": "EybT3EDUcAAw8aA"
    },
    {
      "id": 324,
      "url": "EybT4EvVEAMNFHX"
    },
    {
      "id": 325,
      "url": "EybT5MdVIAUAa2T"
    },
    {
      "id": 326,
      "url": "EyQ2rUGUYAQz1Kf"
    },
    {
      "id": 327,
      "url": "EyQ2C61U8AEsswF"
    },
    {
      "id": 328,
      "url": "ExyKTDmUYAMzeQT"
    },
    {
      "id": 329,
      "url": "ExyKT_3VIAArIS3"
    },
    {
      "id": 330,
      "url": "ExtKt27U8AwmsIV"
    },
    {
      "id": 331,
      "url": "ExOGVxNU8AILYkZ"
    },
    {
      "id": 332,
      "url": "ExOGWsLUUAISOgN"
    },
    {
      "id": 333,
      "url": "ExKW9E2WUAgzJby"
    },
    {
      "id": 334,
      "url": "ExKW-MKXAAI7Jbf"
    },
    {
      "id": 335,
      "url": "ExKW_NuWEAY15Qk"
    },
    {
      "id": 336,
      "url": "Ew6URkTVcAEt8sm"
    },
    {
      "id": 337,
      "url": "Ew5rjpMVEAInG69"
    },
    {
      "id": 338,
      "url": "Ew1-SQMVIAAcA-b"
    },
    {
      "id": 339,
      "url": "Ew1-UEwVcAI-kZY"
    },
    {
      "id": 340,
      "url": "Ew1-VzeVgAIJux5"
    },
    {
      "id": 341,
      "url": "Ew1-XcNUUAQNfLB"
    },
    {
      "id": 342,
      "url": "EwvGFO_VgAEeOnM"
    },
    {
      "id": 343,
      "url": "EwvGIZkUYAEAy38"
    },
    {
      "id": 344,
      "url": "EwvGLxQUUAADF_Y"
    },
    {
      "id": 345,
      "url": "EwrXqzdVkAE9fMh"
    },
    {
      "id": 346,
      "url": "EwPpYZ4VEAYckm-"
    },
    {
      "id": 347,
      "url": "EwMhXDVVoAEJPr3"
    },
    {
      "id": 348,
      "url": "EwMhYIkUcAM4tK8"
    },
    {
      "id": 349,
      "url": "EwMhZp-UcAAo0yC"
    },
    {
      "id": 350,
      "url": "EwCXu_8VIAEh54f"
    },
    {
      "id": 351,
      "url": "EwCXvnxVkAI4R3x"
    },
    {
      "id": 352,
      "url": "EwCXwNHVoAAdpAN"
    },
    {
      "id": 353,
      "url": "Ev8IAvBUcAYK3-e"
    },
    {
      "id": 354,
      "url": "Ev8IBxQUUAMq8Xe"
    },
    {
      "id": 355,
      "url": "Ev8ICvwVcAE6a3L"
    },
    {
      "id": 356,
      "url": "Ev8IDmvVIAIYtaM"
    },
    {
      "id": 357,
      "url": "EvnX0mvVEAMjkPR"
    },
    {
      "id": 358,
      "url": "EuQH50YXUAcZC8y"
    },
    {
      "id": 359,
      "url": "EtxHlmKVIAIa6vf"
    },
    {
      "id": 360,
      "url": "Es9HaebVcAA8WKw"
    },
    {
      "id": 361,
      "url": "Es9Hbl9VoAA03M8"
    },
    {
      "id": 362,
      "url": "Esjc0dmUYAEwnA_"
    },
    {
      "id": 363,
      "url": "Esjc1gXU0AAM_sw"
    },
    {
      "id": 364,
      "url": "Esjc2oyUUAENcpd"
    },
    {
      "id": 365,
      "url": "EsJk-wEUYAQu5n5"
    },
    {
      "id": 366,
      "url": "EsJk_ttUwAcFM9b"
    },
    {
      "id": 367,
      "url": "EsJlBHrUYAEjMOw"
    },
    {
      "id": 368,
      "url": "EsJlCbsVkAUXFtJ"
    },
    {
      "id": 369,
      "url": "EryPJIrU0AcvqaN"
    },
    {
      "id": 370,
      "url": "EryPKVNUYAMFnEt"
    },
    {
      "id": 371,
      "url": "EryPLahU0Ac2TIM"
    },
    {
      "id": 372,
      "url": "EryPMboVoAMivOv"
    },
    {
      "id": 373,
      "url": "Eq8n8z9VEAEpaI4"
    },
    {
      "id": 374,
      "url": "Eq8n-FvVoAEjgTr"
    },
    {
      "id": 375,
      "url": "Eq8n_KiUcAEOoz8"
    },
    {
      "id": 376,
      "url": "Eq8oAL0VQAEijk5"
    },
    {
      "id": 377,
      "url": "EqyDwC3VEAEeRqG"
    },
    {
      "id": 378,
      "url": "EqyDw8MUUAAadSu"
    },
    {
      "id": 379,
      "url": "EqyDxzgVgAEfadd"
    },
    {
      "id": 380,
      "url": "EqyDyrJUYAcv55a"
    },
    {
      "id": 381,
      "url": "EqFCuJIUwAAGSR9"
    },
    {
      "id": 382,
      "url": "EqFCvQrVEAAKSEE"
    },
    {
      "id": 383,
      "url": "EqFCwWZVoAAVU49"
    },
    {
      "id": 384,
      "url": "EqFCxcZUwAA5LtL"
    },
    {
      "id": 385,
      "url": "Ep5vxU0VEAAmDZu"
    },
    {
      "id": 386,
      "url": "Ep5vyl0VoAEpKuh"
    },
    {
      "id": 387,
      "url": "Ep5vzsAUcAAZ0ud"
    },
    {
      "id": 388,
      "url": "Ep5v09BVgAIFxRC"
    },
    {
      "id": 389,
      "url": "EpQ0IM0VgAAOaX0"
    },
    {
      "id": 390,
      "url": "EpQ0JetVgAAmsSW"
    },
    {
      "id": 391,
      "url": "EpQ0KwQVEAADCu8"
    },
    {
      "id": 392,
      "url": "EpGXpFHVgAAIO0B"
    },
    {
      "id": 393,
      "url": "EotLjvGUUAA2IfO"
    },
    {
      "id": 394,
      "url": "EojIf9-UwAEJDcd"
    },
    {
      "id": 395,
      "url": "EojIg_VUcAcWtQU"
    },
    {
      "id": 396,
      "url": "EojIiEWU0AojwFF"
    },
    {
      "id": 397,
      "url": "EojIjN0UUAElOX4"
    },
    {
      "id": 398,
      "url": "Eoh2sXdVoAQMd2U"
    },
    {
      "id": 399,
      "url": "EoZINMIUYAIZBo1"
    },
    {
      "id": 400,
      "url": "EoQGOZbUUAADJgw"
    },
    {
      "id": 401,
      "url": "EoNLLiZVEAEGa2F"
    },
    {
      "id": 402,
      "url": "En_YjGUVgAES1K0"
    },
    {
      "id": 403,
      "url": "En_YkFwUYAAJ1vo"
    },
    {
      "id": 404,
      "url": "En_YlLcVcAM8De8"
    },
    {
      "id": 405,
      "url": "En_YmQ1VcAAML8C"
    },
    {
      "id": 406,
      "url": "En6bowhVoAEZKDq"
    },
    {
      "id": 407,
      "url": "En6bpyJVgAI_Dq2"
    },
    {
      "id": 408,
      "url": "En6bq69UUAE4zBy"
    },
    {
      "id": 409,
      "url": "En6bsADUcAEXvfC"
    },
    {
      "id": 410,
      "url": "En0PpPWXMAEQx3n"
    },
    {
      "id": 411,
      "url": "En0PwDtXcAE9Y34"
    },
    {
      "id": 412,
      "url": "En0PxNLW8AAT5rE"
    },
    {
      "id": 413,
      "url": "EnQdbeEVQAEty1W"
    },
    {
      "id": 414,
      "url": "EnQdceVUwAEG8Po"
    },
    {
      "id": 415,
      "url": "EnQddc1UcAAdYeN"
    },
    {
      "id": 416,
      "url": "EnQdeePVcAAAdGT"
    },
    {
      "id": 417,
      "url": "EnKgJcNVQAEkwhX"
    },
    {
      "id": 418,
      "url": "EnHA4tgVQAABUxy"
    },
    {
      "id": 419,
      "url": "EnHA507VkAIqcNa"
    },
    {
      "id": 420,
      "url": "EnHA64QUwAYoVks"
    },
    {
      "id": 421,
      "url": "Emx4ao7VEAEH3Bb"
    },
    {
      "id": 422,
      "url": "Emx4buYVkAE6KdN"
    },
    {
      "id": 423,
      "url": "Emx4c4mUUAU7FpZ"
    },
    {
      "id": 424,
      "url": "Emx4d_EUUAA6yMm"
    },
    {
      "id": 425,
      "url": "Emwgq1iVkAApxdq"
    },
    {
      "id": 426,
      "url": "Emwgr0qVoAUZB_B"
    },
    {
      "id": 427,
      "url": "EmwgszyVkAA0Rem"
    },
    {
      "id": 428,
      "url": "Emwgt4iVoAMt_H8"
    },
    {
      "id": 429,
      "url": "Emstj0hUUAIwuTU"
    },
    {
      "id": 430,
      "url": "Emstk04VQAEG_TL"
    },
    {
      "id": 431,
      "url": "Emstl0cVkAEAIGc"
    },
    {
      "id": 432,
      "url": "Emstm1xVcAA3sVC"
    },
    {
      "id": 433,
      "url": "EmOGjgpU0AAjbQJ"
    },
    {
      "id": 434,
      "url": "EleYnIJUcAAmh0f"
    },
    {
      "id": 435,
      "url": "Ek7uV67VgAAKso9"
    },
    {
      "id": 436,
      "url": "Ek7uZnbUwAMIu9I"
    },
    {
      "id": 437,
      "url": "EkbkWdLU0AAZoFn"
    },
    {
      "id": 438,
      "url": "EkWSnOsUcAAm7mt"
    },
    {
      "id": 439,
      "url": "EkWSoDLUcAEz77X"
    },
    {
      "id": 440,
      "url": "EkWSo3OVoAA7LCB"
    },
    {
      "id": 441,
      "url": "EjyXluyVoAEg7jv"
    },
    {
      "id": 442,
      "url": "EjyXnHGU8AA4HXd"
    },
    {
      "id": 443,
      "url": "EjyXoQwVcAAo0T4"
    },
    {
      "id": 444,
      "url": "EjyXpbzVkAApHCR"
    },
    {
      "id": 445,
      "url": "Ejv5xLRU8AAYP2i"
    },
    {
      "id": 446,
      "url": "EjtN8K5U4AIdBS5"
    },
    {
      "id": 447,
      "url": "EjtN9ZLU8AAioc-"
    },
    {
      "id": 448,
      "url": "EjtN-6NUcAA5NgH"
    },
    {
      "id": 449,
      "url": "EjtOAiEVoAALpUe"
    },
    {
      "id": 450,
      "url": "EjYYkD3U0AEjaoD"
    },
    {
      "id": 451,
      "url": "EjYYlOQVgAAilaR"
    },
    {
      "id": 452,
      "url": "EjYYmT-VoAAv88X"
    },
    {
      "id": 453,
      "url": "EjKelxzUYAEA1ou"
    },
    {
      "id": 454,
      "url": "EjJUKZOUcAAqxBv"
    },
    {
      "id": 455,
      "url": "EjGISCYUcAA1yCP"
    },
    {
      "id": 456,
      "url": "Ei-o6lWUcAAsjva"
    },
    {
      "id": 457,
      "url": "Ei-o8NaU4AAt3ui"
    },
    {
      "id": 458,
      "url": "Ei-o9umUwAAG_4k"
    },
    {
      "id": 459,
      "url": "EifwSo6U4AEyhSL"
    },
    {
      "id": 460,
      "url": "EiRpPbSU4AAvYy8"
    },
    {
      "id": 461,
      "url": "EiRpQdYUYAIb0_2"
    },
    {
      "id": 462,
      "url": "EiRpRp6UYAADI0J"
    },
    {
      "id": 463,
      "url": "EiQhOrjU0AA1Dy5"
    },
    {
      "id": 464,
      "url": "EiQhPdhVkAAesu3"
    },
    {
      "id": 465,
      "url": "EiQhQapUYAA1tp6"
    },
    {
      "id": 466,
      "url": "EiLIAQjU0AEKR5Y"
    },
    {
      "id": 467,
      "url": "EiLIB5CVoAAZFC8"
    },
    {
      "id": 468,
      "url": "EiLIDuDUYAEyWGU"
    },
    {
      "id": 469,
      "url": "EiHt8pNUYAQfGFn"
    },
    {
      "id": 470,
      "url": "EiFn52nUYAMq_Kw"
    },
    {
      "id": 471,
      "url": "EiBHyGwVgAAB7u_"
    },
    {
      "id": 472,
      "url": "EhsT4PZUMAAdxO7"
    },
    {
      "id": 473,
      "url": "EhsT5G2UYAIrwUw"
    },
    {
      "id": 474,
      "url": "EhsT6VNU8AAt4Ci"
    },
    {
      "id": 475,
      "url": "EhsT7K3VoAIjHtI"
    },
    {
      "id": 476,
      "url": "EhjUfCLUMAQx-hP"
    },
    {
      "id": 477,
      "url": "EhjUgF0VgAAZ2U4"
    },
    {
      "id": 478,
      "url": "EhjUhEzU4AAoXS-"
    },
    {
      "id": 479,
      "url": "EhivHA9UMAAx_M5"
    },
    {
      "id": 480,
      "url": "EhfrUt5U8AAM6HN"
    },
    {
      "id": 481,
      "url": "EhDG3P0UcAA0F6K"
    },
    {
      "id": 482,
      "url": "EhDG4rpVkAAQxRS"
    },
    {
      "id": 483,
      "url": "EhDG57UVoAAEF9y"
    },
    {
      "id": 484,
      "url": "EhDG7UFUYAA572F"
    },
    {
      "id": 485,
      "url": "Eg9-eQrU0AEC6R2"
    },
    {
      "id": 486,
      "url": "Eg9-e8JU4AAgDhW"
    },
    {
      "id": 487,
      "url": "Eg9-fmAU8AUN1AV"
    },
    {
      "id": 488,
      "url": "Eggr6l9VoAIxP8D"
    },
    {
      "id": 489,
      "url": "Ef_0EGWUwAAUsVA"
    },
    {
      "id": 490,
      "url": "Ef7oOKuU8AABkba"
    },
    {
      "id": 491,
      "url": "Ef7oPfYVAAEUgQM"
    },
    {
      "id": 492,
      "url": "Ef7oQ1qVoAEqfAK"
    },
    {
      "id": 493,
      "url": "Ef7oR-jU8AE7F1_"
    },
    {
      "id": 494,
      "url": "Efhaw4sUEAEwtyU"
    },
    {
      "id": 495,
      "url": "EfhayZlU4AE2HFE"
    },
    {
      "id": 496,
      "url": "EfW4JeZUwAAWE05"
    },
    {
      "id": 497,
      "url": "EfW4KzfUYAA4jK3"
    },
    {
      "id": 498,
      "url": "EfW4MKUVoAEFzth"
    },
    {
      "id": 499,
      "url": "EfW4NLmUcAAPjqs"
    },
    {
      "id": 500,
      "url": "EfRw6SlUMAcr8Qx"
    },
    {
      "id": 501,
      "url": "EfRw7mFVAAE_gH7"
    },
    {
      "id": 502,
      "url": "EfRw82UUcAIGreJ"
    },
    {
      "id": 503,
      "url": "EfRw-MGUMAEvgz_"
    },
    {
      "id": 504,
      "url": "EfMuoahU0AECHLf"
    },
    {
      "id": 505,
      "url": "EfMup1gUwAEYL0E"
    },
    {
      "id": 506,
      "url": "EfMurCIVAAE17Uq"
    },
    {
      "id": 507,
      "url": "EfMusSIUcAAXIYV"
    },
    {
      "id": 508,
      "url": "EeVzFypUcAAmE9U"
    },
    {
      "id": 509,
      "url": "EeVzGy3UEAEztsn"
    },
    {
      "id": 510,
      "url": "EeUpW5aVoAMgLUh"
    },
    {
      "id": 511,
      "url": "EeUpYh2U4AMKfTk"
    },
    {
      "id": 512,
      "url": "EeUpaQNU4AELTdi"
    },
    {
      "id": 513,
      "url": "EeUpbmRUEAA5R5Q"
    },
    {
      "id": 514,
      "url": "EeTYblFUcAYZScZ"
    },
    {
      "id": 515,
      "url": "Ec3bgnsUYAEP0hI"
    },
    {
      "id": 516,
      "url": "EcuGNVZVcAAp3_b"
    },
    {
      "id": 517,
      "url": "EcswfzoUcAE9hSE"
    },
    {
      "id": 518,
      "url": "EcI97TZUcAEum3o"
    },
    {
      "id": 519,
      "url": "Eb5QHmyUwAAJwob"
    },
    {
      "id": 520,
      "url": "Eb5QIJ1U4AAdxFH"
    },
    {
      "id": 521,
      "url": "Eb5QIkLVcAAR-sE"
    },
    {
      "id": 522,
      "url": "Eb5QI_IUEAEc_73"
    },
    {
      "id": 523,
      "url": "Eb0J3XNU4AYgRGv"
    },
    {
      "id": 524,
      "url": "Ebu_69yU0AAArDK"
    },
    {
      "id": 525,
      "url": "Ebp1EjAU8AE089L"
    },
    {
      "id": 526,
      "url": "EblE59XU0AE1POZ"
    },
    {
      "id": 527,
      "url": "EbfikExU8AESIQJ"
    },
    {
      "id": 528,
      "url": "EbaU0nDUYAE2uNL"
    },
    {
      "id": 529,
      "url": "EbVP8THUcAA2xK8"
    },
    {
      "id": 530,
      "url": "EbVP9mOU8AEs2de"
    },
    {
      "id": 531,
      "url": "EbPPV9xUMAAZIsM"
    },
    {
      "id": 532,
      "url": "EbKE9IWVcAAMF-G"
    },
    {
      "id": 533,
      "url": "EbKE-fOUMAEfFBf"
    },
    {
      "id": 534,
      "url": "EbKE_zpUEAAowit"
    },
    {
      "id": 535,
      "url": "EbF-86rUcAYNL6z"
    },
    {
      "id": 536,
      "url": "EbF_QTWUcAEqcGp"
    },
    {
      "id": 537,
      "url": "EbAnpZ4UMAAW4q2"
    },
    {
      "id": 538,
      "url": "EbAnqxXVAAADyIy"
    },
    {
      "id": 539,
      "url": "Ea9RNunUwAAS7D_"
    },
    {
      "id": 540,
      "url": "Ea7eYUoUYAAE5oI"
    },
    {
      "id": 541,
      "url": "Ea7eZfnU8AEZNKP"
    },
    {
      "id": 542,
      "url": "Ea2WJGjU4AAtvfC"
    },
    {
      "id": 543,
      "url": "Ea2WKJkUwAYdG41"
    },
    {
      "id": 544,
      "url": "Ea2WLKpUEAAp4bD"
    },
    {
      "id": 545,
      "url": "EaxL40UUwAIHTDO"
    },
    {
      "id": 546,
      "url": "EaxL68JVAAElCVY"
    },
    {
      "id": 547,
      "url": "EasEAscXkAE1BCa"
    },
    {
      "id": 548,
      "url": "EasEByYXsAAhe-C"
    },
    {
      "id": 549,
      "url": "Eam5JkhU4AAyUpz"
    },
    {
      "id": 550,
      "url": "Eam5K5jU8AAI-Fi"
    },
    {
      "id": 551,
      "url": "Eah8SPNU4AAj5rs"
    },
    {
      "id": 552,
      "url": "EahwdlKUMAUeK6X"
    },
    {
      "id": 553,
      "url": "Eahwe5wUMAE1nAJ"
    },
    {
      "id": 554,
      "url": "EacoImqVAAAy1Pe"
    },
    {
      "id": 555,
      "url": "EacoJmlUwAAvfmF"
    },
    {
      "id": 556,
      "url": "EacoLE9UYAA5nZK"
    },
    {
      "id": 557,
      "url": "EacoMfzUMAY0sPb"
    },
    {
      "id": 558,
      "url": "EaXfSBqU0AIlDmp"
    },
    {
      "id": 559,
      "url": "EaXfTIsUcAAxnJu"
    },
    {
      "id": 560,
      "url": "EaXfUVfUMAAMQRl"
    },
    {
      "id": 561,
      "url": "EaSQyCoUwAAs__5"
    },
    {
      "id": 562,
      "url": "EaSQzVdUcAE0yRb"
    },
    {
      "id": 563,
      "url": "EaNI5jxUMAAl0jM"
    },
    {
      "id": 564,
      "url": "EaNI641U8AA4CUj"
    },
    {
      "id": 565,
      "url": "EaNI8EsU4AEE3UB"
    },
    {
      "id": 566,
      "url": "EaIFVTHU0AAdsEw"
    },
    {
      "id": 567,
      "url": "EaIFWQOUwAEQyA_"
    },
    {
      "id": 568,
      "url": "EaC35D7UYAEMJp6"
    },
    {
      "id": 569,
      "url": "EaC35-0VAAAQ6Wk"
    },
    {
      "id": 570,
      "url": "EZ9uRCPU0AIwSWo"
    },
    {
      "id": 571,
      "url": "EZ9uSi0UMAAAxLh"
    },
    {
      "id": 572,
      "url": "EZ9uTynVAAE73-i"
    },
    {
      "id": 573,
      "url": "EZ6JqY8U8AoZ9md"
    },
    {
      "id": 574,
      "url": "EZ4lLoHUwAAo7ll"
    },
    {
      "id": 575,
      "url": "EZ4lNBgU0AAcI2J"
    },
    {
      "id": 576,
      "url": "EZ4lOHqU8AAKGdp"
    },
    {
      "id": 577,
      "url": "EZzYCS5UwAEdcF9"
    },
    {
      "id": 578,
      "url": "EZuRjjVUcAAIlWV"
    },
    {
      "id": 579,
      "url": "EZuRlC8UYAIHhG_"
    },
    {
      "id": 580,
      "url": "EZuRmcoUYAE3DJe"
    },
    {
      "id": 581,
      "url": "EZpE07KU8AAIZu7"
    },
    {
      "id": 582,
      "url": "EZpE2ehUMAEgsG0"
    },
    {
      "id": 583,
      "url": "EZj9h-IUEAAbrQo"
    },
    {
      "id": 584,
      "url": "EZj9jElUwAArpxs"
    },
    {
      "id": 585,
      "url": "EZezA6mUYAA9ctr"
    },
    {
      "id": 586,
      "url": "EZezCUvUMAADsE3"
    },
    {
      "id": 587,
      "url": "EZZpejqUwAEiLdX"
    },
    {
      "id": 588,
      "url": "EZZpfobUwAAnt_6"
    },
    {
      "id": 589,
      "url": "EZZpgbWUwAE3PCH"
    },
    {
      "id": 590,
      "url": "EZZphSRVcAAcJhT"
    },
    {
      "id": 591,
      "url": "EZUewwZUwAc7RL1"
    },
    {
      "id": 592,
      "url": "EZUeyMnUwAImUdS"
    },
    {
      "id": 593,
      "url": "EZPYKzbUwAAkDo8"
    },
    {
      "id": 594,
      "url": "EZPYMe8UEAMcQ1y"
    },
    {
      "id": 595,
      "url": "EZPYOM6UMAACaig"
    },
    {
      "id": 596,
      "url": "EZPYPkvU8AEe-Oq"
    },
    {
      "id": 597,
      "url": "EZKK7M0VcAECkBY"
    },
    {
      "id": 598,
      "url": "EZKK8q8VcAEhs4u"
    },
    {
      "id": 599,
      "url": "EZKK-FQUMAMyn1C"
    },
    {
      "id": 600,
      "url": "EZKK_kEUYAYAxjG"
    },
    {
      "id": 601,
      "url": "EZFEn5KUYAAneYX"
    },
    {
      "id": 602,
      "url": "EZFEpZBVcAA4wua"
    },
    {
      "id": 603,
      "url": "EZFEqWCVcAAEnhv"
    },
    {
      "id": 604,
      "url": "EZFErcBVcAAOTYA"
    },
    {
      "id": 605,
      "url": "EY_4AsGWoAkQEhj"
    },
    {
      "id": 606,
      "url": "EY_4CcwWAAYhvHR"
    },
    {
      "id": 607,
      "url": "EY_4D6OXYAQmb1U"
    },
    {
      "id": 608,
      "url": "EY_4FTpWoAog-aa"
    },
    {
      "id": 609,
      "url": "EY61msCUcAApdMq"
    },
    {
      "id": 610,
      "url": "EY61oBnVcAATFKN"
    },
    {
      "id": 611,
      "url": "EY61pK6UwAAG738"
    },
    {
      "id": 612,
      "url": "EY1nTr_UEAAU21P"
    },
    {
      "id": 613,
      "url": "EY1nVOMU4AAmQCP"
    },
    {
      "id": 614,
      "url": "EYyYf8bUMAE3Zvz"
    },
    {
      "id": 615,
      "url": "EYwjhzxU8AUg9WJ"
    },
    {
      "id": 616,
      "url": "EYwjjuaUwAA7TLO"
    },
    {
      "id": 617,
      "url": "EYwjlYmUwAA1SEv"
    },
    {
      "id": 618,
      "url": "EYwjmzmUYAA_2j7"
    },
    {
      "id": 619,
      "url": "EYrRZL0UcAAeXjP"
    },
    {
      "id": 620,
      "url": "EYrRayYVcAA-INb"
    },
    {
      "id": 621,
      "url": "EYrRcUXUYAAh63M"
    },
    {
      "id": 622,
      "url": "EYrRdrsVAAAC9Bd"
    },
    {
      "id": 623,
      "url": "EYmHyRdUYAE0C5_"
    },
    {
      "id": 624,
      "url": "EYmHzsjVcAAP4na"
    },
    {
      "id": 625,
      "url": "EYmH1LPUYAEk0Ij"
    },
    {
      "id": 626,
      "url": "EYmH2fyU4AUJVKe"
    },
    {
      "id": 627,
      "url": "EYg_w7eVAAILCGX"
    },
    {
      "id": 628,
      "url": "EYg_xy0VcAEbK02"
    },
    {
      "id": 629,
      "url": "EYg_yzCUMAMFm12"
    },
    {
      "id": 630,
      "url": "EYg_0bCU8AA1pdU"
    },
    {
      "id": 631,
      "url": "EYb4E0oUMAAutdH"
    },
    {
      "id": 632,
      "url": "EYb4GPbU0AAQjDl"
    },
    {
      "id": 633,
      "url": "EYZO71gUMAAqjhW"
    },
    {
      "id": 634,
      "url": "EYZO9P7U4AAUNTY"
    },
    {
      "id": 635,
      "url": "EYZO-7gUYAA9lNy"
    },
    {
      "id": 636,
      "url": "EYWrR2mUwAE2Xbh"
    },
    {
      "id": 637,
      "url": "EYWrTh3U8AAA8jk"
    },
    {
      "id": 638,
      "url": "EYWrVKBUEAAgo2M"
    },
    {
      "id": 639,
      "url": "EYWrWznU4AAh7AB"
    },
    {
      "id": 640,
      "url": "EYRikQyU4AA5cpQ"
    },
    {
      "id": 641,
      "url": "EYRilqLU8AAwXVC"
    },
    {
      "id": 642,
      "url": "EYRim-EUcAE7IIT"
    },
    {
      "id": 643,
      "url": "EYRioW8UEAAb7QO"
    },
    {
      "id": 644,
      "url": "EYMYLOfVcAI4zEK"
    },
    {
      "id": 645,
      "url": "EYMYMuvUMAAgJjI"
    },
    {
      "id": 646,
      "url": "EYMYOCoUYAE4HQK"
    },
    {
      "id": 647,
      "url": "EYMYPPCUEAAMCt-"
    },
    {
      "id": 648,
      "url": "EYHNmSZUYAEQDZ7"
    },
    {
      "id": 649,
      "url": "EYHNoX3UMAAjdUV"
    },
    {
      "id": 650,
      "url": "EYHNqQjVcAI68l3"
    },
    {
      "id": 651,
      "url": "EYCGZ-cUMAErcFO"
    },
    {
      "id": 652,
      "url": "EYCGbu3UwAAQJVH"
    },
    {
      "id": 653,
      "url": "EYCGdMtUYAEo84r"
    },
    {
      "id": 654,
      "url": "EYCGek4UYAAWAo_"
    },
    {
      "id": 655,
      "url": "EX9BkhcUEAAKqCo"
    },
    {
      "id": 656,
      "url": "EX9BmCzU8AI-Ino"
    },
    {
      "id": 657,
      "url": "EX9Bnq2U4AAwn-e"
    },
    {
      "id": 658,
      "url": "EX9BpF9UwAAf5Qv"
    },
    {
      "id": 659,
      "url": "EX48SafUEAA79dQ"
    },
    {
      "id": 660,
      "url": "EX3wCgSXsAAtGTI"
    },
    {
      "id": 661,
      "url": "EX3wEMtWsAI_zr2"
    },
    {
      "id": 662,
      "url": "EXyriqzUMAIp5Oo"
    },
    {
      "id": 663,
      "url": "EXyrkbxUMAEe_fV"
    },
    {
      "id": 664,
      "url": "EXyrloMU0AAZbyx"
    },
    {
      "id": 665,
      "url": "EXyrnPIUcAA1y0g"
    },
    {
      "id": 666,
      "url": "EXtglIVUwAIDpCo"
    },
    {
      "id": 667,
      "url": "EXtgmy0UwAAgSzv"
    },
    {
      "id": 668,
      "url": "EXtgoU6VAAApuGW"
    },
    {
      "id": 669,
      "url": "EXtgppWU8AMdZ2N"
    },
    {
      "id": 670,
      "url": "EXoZ857VAAEIYd2"
    },
    {
      "id": 671,
      "url": "EXoZ-LzUMAEImSh"
    },
    {
      "id": 672,
      "url": "EXoaAJOVAAAbe-5"
    },
    {
      "id": 673,
      "url": "EXoaBcSUwAEwZJf"
    },
    {
      "id": 674,
      "url": "EXjOhHWUcAA92sR"
    },
    {
      "id": 675,
      "url": "EXjOigJVAAEDo5n"
    },
    {
      "id": 676,
      "url": "EXjOjs-U8AAY_3Z"
    },
    {
      "id": 677,
      "url": "EXjOknkVcAE-lNv"
    },
    {
      "id": 678,
      "url": "EXeAbPEU8AAtyVe"
    },
    {
      "id": 679,
      "url": "EXeAco4U8AATiaX"
    },
    {
      "id": 680,
      "url": "EXeAd6xUwAAh0wC"
    },
    {
      "id": 681,
      "url": "EXeAe7_U8AIuUaU"
    },
    {
      "id": 682,
      "url": "EXY9eUlVcAA__kO"
    },
    {
      "id": 683,
      "url": "EXY9fbNUcAE7lYZ"
    },
    {
      "id": 684,
      "url": "EXY9gzkU0AAalom"
    },
    {
      "id": 685,
      "url": "EXY9iG6U4AIoXF1"
    },
    {
      "id": 686,
      "url": "EXT0i0aUcAAr7lw"
    },
    {
      "id": 687,
      "url": "EXT0kSKUwAIBMjJ"
    },
    {
      "id": 688,
      "url": "EXT0lliVAAEUUy0"
    },
    {
      "id": 689,
      "url": "EXT0m1TUwAAMGLW"
    },
    {
      "id": 690,
      "url": "EXOpOsEUYAAzo0-"
    },
    {
      "id": 691,
      "url": "EXOpPxzU0AA16cn"
    },
    {
      "id": 692,
      "url": "EXOpRGRVcAA8lyF"
    },
    {
      "id": 693,
      "url": "EXOpSHcUEAEYQJb"
    },
    {
      "id": 694,
      "url": "EXJlFwjUEAAQ2-r"
    },
    {
      "id": 695,
      "url": "EXJlHVzVAAEsi2y"
    },
    {
      "id": 696,
      "url": "EXJlJEEUcAMBZ1V"
    },
    {
      "id": 697,
      "url": "EXJlKs9UMAMF-Ln"
    },
    {
      "id": 698,
      "url": "EXEcdXBUcAA2VYN"
    },
    {
      "id": 699,
      "url": "EXEcexhU8AA9DyZ"
    },
    {
      "id": 700,
      "url": "EXEcgGfVcAEH0Fx"
    },
    {
      "id": 701,
      "url": "EXEchfhU0AETDzA"
    },
    {
      "id": 702,
      "url": "EW_PoCBUcAA_oP7"
    },
    {
      "id": 703,
      "url": "EW_PptCUYAESyJL"
    },
    {
      "id": 704,
      "url": "EW_PrcQUEAIMKnc"
    },
    {
      "id": 705,
      "url": "EW_PsxNUMAA6bRD"
    },
    {
      "id": 706,
      "url": "EW6C_XCUcAEy9_Y"
    },
    {
      "id": 707,
      "url": "EW6DAbsU8AEFL0Q"
    },
    {
      "id": 708,
      "url": "EW6DBlqVAAA0tid"
    },
    {
      "id": 709,
      "url": "EW6DC3NU0AAi5SJ"
    },
    {
      "id": 710,
      "url": "EW3pc3uUMAAcD3f"
    },
    {
      "id": 711,
      "url": "EW05ymZU0AAugiK"
    },
    {
      "id": 712,
      "url": "EW050GAUYAM1SLA"
    },
    {
      "id": 713,
      "url": "EW051riUwAAL_vK"
    },
    {
      "id": 714,
      "url": "EW053TwVAAExqMJ"
    },
    {
      "id": 715,
      "url": "EWvyRrfWoAEhN5K"
    },
    {
      "id": 716,
      "url": "EWvyTqNXkAAJ8lZ"
    },
    {
      "id": 717,
      "url": "EWvyVVQX0AU-gSb"
    },
    {
      "id": 718,
      "url": "EWvyWWZWkAAhHRO"
    },
    {
      "id": 719,
      "url": "EWqlbeRU4AEm4Kw"
    },
    {
      "id": 720,
      "url": "EWqldDNVcAAfKv6"
    },
    {
      "id": 721,
      "url": "EWqlepZUYAEDyLq"
    },
    {
      "id": 722,
      "url": "EWqlfs5VAAAXR6Y"
    },
    {
      "id": 723,
      "url": "EWlfOYFUwAEGKa4"
    },
    {
      "id": 724,
      "url": "EWlfPxdVcAEyxB5"
    },
    {
      "id": 725,
      "url": "EWlfQ3yU8AU-Eui"
    },
    {
      "id": 726,
      "url": "EWlfSHTU4AApAd3"
    },
    {
      "id": 727,
      "url": "EWgSqp_VAAENsJe"
    },
    {
      "id": 728,
      "url": "EWgSr-HVAAAJkyJ"
    },
    {
      "id": 729,
      "url": "EWgStqgU8AEn_BU"
    },
    {
      "id": 730,
      "url": "EWbJZE0VcAEDX1G"
    },
    {
      "id": 731,
      "url": "EWbJamzVcAIAvDV"
    },
    {
      "id": 732,
      "url": "EWbJcUKUEAYA-co"
    },
    {
      "id": 733,
      "url": "EWWGMv-U4AAzHxX"
    },
    {
      "id": 734,
      "url": "EWWGOX7UwAEFVRL"
    },
    {
      "id": 735,
      "url": "EWWGPZ0UMAEzPBh"
    },
    {
      "id": 736,
      "url": "EWSjEslXkAAT2kB"
    },
    {
      "id": 737,
      "url": "EWSjE95XsAARo8d"
    },
    {
      "id": 738,
      "url": "EWSjFRXXQAEiJQU"
    },
    {
      "id": 739,
      "url": "EWSjFdjXYAAXKIk"
    },
    {
      "id": 740,
      "url": "EWQz1aVUwAAfcAQ"
    },
    {
      "id": 741,
      "url": "EWQz2-UUwAYabzX"
    },
    {
      "id": 742,
      "url": "EWQz4QKU4AYIC82"
    },
    {
      "id": 743,
      "url": "EWQz5e6UYAExN3U"
    },
    {
      "id": 744,
      "url": "EWL20qaU4AAjZO5"
    },
    {
      "id": 745,
      "url": "EWL22U1U8AgDiQ_"
    },
    {
      "id": 746,
      "url": "EWL23pMUYAEMeyA"
    },
    {
      "id": 747,
      "url": "EWL25WQUMAEDeGK"
    },
    {
      "id": 748,
      "url": "EWG69H0UEAEXLrY"
    },
    {
      "id": 749,
      "url": "EWG69xtUEAAIiPS"
    },
    {
      "id": 750,
      "url": "EWBfQ_GU0AApyFu"
    },
    {
      "id": 751,
      "url": "EWBfRtDVcAIdkKY"
    },
    {
      "id": 752,
      "url": "EWBfSNaUMAEuo2Y"
    },
    {
      "id": 753,
      "url": "EV8MvYRUYAE0q5N"
    },
    {
      "id": 754,
      "url": "EV8MxD4UYAA0XHj"
    },
    {
      "id": 755,
      "url": "EV8MywFVAAEwZDm"
    },
    {
      "id": 756,
      "url": "EV3O-fBUMAAvjDv"
    },
    {
      "id": 757,
      "url": "EV3O_GAVAAAHZhP"
    },
    {
      "id": 758,
      "url": "EV3O_tqU8AAD5t4"
    },
    {
      "id": 759,
      "url": "EVx-LbUWsAIllKk"
    },
    {
      "id": 760,
      "url": "EVx-MNoWoAEbkGj"
    },
    {
      "id": 761,
      "url": "EVx-NZdUwAEL4nd"
    },
    {
      "id": 762,
      "url": "EVstpFTU4AAoBk5"
    },
    {
      "id": 763,
      "url": "EVstp9qVcAAsaQZ"
    },
    {
      "id": 764,
      "url": "EVstqrCUMAAPniN"
    },
    {
      "id": 765,
      "url": "EVnu7GOUUAIcgrw"
    },
    {
      "id": 766,
      "url": "EVnu8bFU0AAks2t"
    },
    {
      "id": 767,
      "url": "EVnu-i3U0AAUc_3"
    },
    {
      "id": 768,
      "url": "EVifN8iU8AEMBrl"
    },
    {
      "id": 769,
      "url": "EVifOisU8AAy_6u"
    },
    {
      "id": 770,
      "url": "EVdbBjKUYAc36Vg"
    },
    {
      "id": 771,
      "url": "EVdbH5LUMAE7HYJ"
    },
    {
      "id": 772,
      "url": "EVdbIgaU4AIbSCY"
    },
    {
      "id": 773,
      "url": "EVYP9PXUwAAZ4HG"
    },
    {
      "id": 774,
      "url": "EVYP-uqU8AARezN"
    },
    {
      "id": 775,
      "url": "EVS_NKGU0AETFbU"
    },
    {
      "id": 776,
      "url": "EVS_OSdUwAAXEKj"
    },
    {
      "id": 777,
      "url": "EVS_Pl0U4AAVIbr"
    },
    {
      "id": 778,
      "url": "EVN3O4FVAAkJPmd"
    },
    {
      "id": 779,
      "url": "EVN3QxVUwAMSL7k"
    },
    {
      "id": 780,
      "url": "EVN3SQwUYAM2D6j"
    },
    {
      "id": 781,
      "url": "EVIw-h1UYAA2ck6"
    },
    {
      "id": 782,
      "url": "EVIw_FQU8AI0F2W"
    },
    {
      "id": 783,
      "url": "EVIw_i1VAAAl2Dy"
    },
    {
      "id": 784,
      "url": "EVD1Jr8UMAE30fP"
    },
    {
      "id": 785,
      "url": "EVD1K_EUYAAyAp2"
    },
    {
      "id": 786,
      "url": "EU-hVCvUYAAC07R"
    },
    {
      "id": 787,
      "url": "EU-hVwOU0AAcBQ-"
    },
    {
      "id": 788,
      "url": "EU5XTWyUwAACO6O"
    },
    {
      "id": 789,
      "url": "EU5XT9xU8AAwwd5"
    },
    {
      "id": 790,
      "url": "EU0Rb6fUYAAs454"
    },
    {
      "id": 791,
      "url": "EU0RdPvUwAIRudt"
    },
    {
      "id": 792,
      "url": "EUuzXY9U0AA791t"
    },
    {
      "id": 793,
      "url": "EUuzYGLU4AI8rzw"
    },
    {
      "id": 794,
      "url": "EUpwedaUMAE4x_D"
    },
    {
      "id": 795,
      "url": "EUpwfLIU0AAN4j1"
    },
    {
      "id": 796,
      "url": "EUkwSmfU8AEVbbO"
    },
    {
      "id": 797,
      "url": "EUkwS0iUwAIWn0b"
    },
    {
      "id": 798,
      "url": "EUfudqWUwAE0lje"
    },
    {
      "id": 799,
      "url": "EUfufizUUAEHqiI"
    },
    {
      "id": 800,
      "url": "EUfuhDeU8AMTOuO"
    },
    {
      "id": 801,
      "url": "EUapXweU0AA8MqT"
    },
    {
      "id": 802,
      "url": "EUapYVfUEAImYn6"
    },
    {
      "id": 803,
      "url": "EUVewPNU0AAz9wd"
    },
    {
      "id": 804,
      "url": "EUVeybdVAAAHqRN"
    },
    {
      "id": 805,
      "url": "EUQP-KSVAAE7dYI"
    },
    {
      "id": 806,
      "url": "EUQP_t2UcAI2EVg"
    },
    {
      "id": 807,
      "url": "EUQQBQPUwAE9Tup"
    },
    {
      "id": 808,
      "url": "EULKeWcU0AEtA8T"
    },
    {
      "id": 809,
      "url": "EULKfumVAAEYs-f"
    },
    {
      "id": 810,
      "url": "EUGCfUsU8AACFrL"
    },
    {
      "id": 811,
      "url": "EUBCmkdUYAIofGA"
    },
    {
      "id": 812,
      "url": "EUBCnXNUwAE6zem"
    },
    {
      "id": 813,
      "url": "ET7YZvfUcAAtcko"
    },
    {
      "id": 814,
      "url": "ET7YaSXU4AAfFh9"
    },
    {
      "id": 815,
      "url": "ET7YaygUUAANyjy"
    },
    {
      "id": 816,
      "url": "ETybd_pUYAEPGCk"
    },
    {
      "id": 817,
      "url": "ETybfjHUwAEdfrH"
    },
    {
      "id": 818,
      "url": "ETybhALUMAAMmd5"
    },
    {
      "id": 819,
      "url": "ETybi-fU0AEp6RH"
    },
    {
      "id": 820,
      "url": "ETtGWVhUcAEnIVz"
    },
    {
      "id": 821,
      "url": "ETidHsrUUAAaMTv"
    },
    {
      "id": 822,
      "url": "ETSutqkUwAEKOH1"
    },
    {
      "id": 823,
      "url": "ETQG3YpUUAY7Z-r"
    },
    {
      "id": 824,
      "url": "ETQG4EYUYAATiIU"
    },
    {
      "id": 825,
      "url": "ETQG5H8UUAEb9dt"
    },
    {
      "id": 826,
      "url": "ETQGaCnUUAwYUDE"
    },
    {
      "id": 827,
      "url": "ETQGcU6UUAI0O8p"
    },
    {
      "id": 828,
      "url": "ETQGdwjUUAUluXb"
    },
    {
      "id": 829,
      "url": "ETQGfAZU0AAZyIn"
    },
    {
      "id": 830,
      "url": "ETPHBx2UYAIXN1T"
    },
    {
      "id": 831,
      "url": "ESqaAJaUMAETr66"
    },
    {
      "id": 832,
      "url": "ESRuIeYUEAUnaCA"
    },
    {
      "id": 833,
      "url": "ESRuJ7KUUAA8_rt"
    },
    {
      "id": 834,
      "url": "ESPY_q1UcAIb3Tq"
    },
    {
      "id": 835,
      "url": "ESKGbSXUcAAy9Vt"
    },
    {
      "id": 836,
      "url": "ERcq6rIUwAEzDlo"
    },
    {
      "id": 837,
      "url": "EQ0ijexU4AErOdr"
    },
    {
      "id": 838,
      "url": "EQ0ikN_VAAAR-yY"
    },
    {
      "id": 839,
      "url": "EQ0ik-XUwAIoMiT"
    },
    {
      "id": 840,
      "url": "EQ0ilrCUwAU2ZU5"
    },
    {
      "id": 841,
      "url": "EQoCtymVUAA9kl7"
    },
    {
      "id": 842,
      "url": "EQknJ5ZUwAUmND4"
    },
    {
      "id": 843,
      "url": "EQf0SO0VUAAQFJ4"
    },
    {
      "id": 844,
      "url": "EQfwLGPUYAUc1Vo"
    },
    {
      "id": 845,
      "url": "EPxVj_OUcAINmNR"
    },
    {
      "id": 846,
      "url": "EPxVlTQU0AIyy3O"
    },
    {
      "id": 847,
      "url": "EPvqmeyU8AIqD3k"
    },
    {
      "id": 848,
      "url": "EPvqg-mUcAAqHmp"
    },
    {
      "id": 849,
      "url": "EPvqinwUUAAEPGf"
    },
    {
      "id": 850,
      "url": "EPvqkL7VAAES30G"
    },
    {
      "id": 851,
      "url": "EPsR6qfUcAEfBCL"
    },
    {
      "id": 852,
      "url": "EPsR8SkVAAASXbX"
    },
    {
      "id": 853,
      "url": "EPsR-Q_U4AYOE9o"
    },
    {
      "id": 854,
      "url": "EPqM6TkUcAErirG"
    },
    {
      "id": 855,
      "url": "EPnPQQQUcAEeoZf"
    },
    {
      "id": 856,
      "url": "EPdOdcRU4AArvzc"
    },
    {
      "id": 857,
      "url": "EPdOfGXUcAE1pse"
    },
    {
      "id": 858,
      "url": "EPDVvmXUcAAlcFY"
    },
    {
      "id": 859,
      "url": "EO-Bb1jUUAAQ4t2"
    },
    {
      "id": 860,
      "url": "EOyXO4WUwAA7CI4"
    },
    {
      "id": 861,
      "url": "EOxY0QXU0AINcey"
    },
    {
      "id": 862,
      "url": "EOuVwMBU8AAJ1rE"
    },
    {
      "id": 863,
      "url": "EOtOUl5VUAAmLGs"
    },
    {
      "id": 864,
      "url": "EOpqtLkVUAEBwaH"
    },
    {
      "id": 865,
      "url": "EOoWrSvU8AUSx1N"
    },
    {
      "id": 866,
      "url": "EOi4pskU4AEiUrd"
    },
    {
      "id": 867,
      "url": "EOTNNG-VAAMgII_"
    },
    {
      "id": 868,
      "url": "EOTNOjAUEAEyVuV"
    },
    {
      "id": 869,
      "url": "EOTNP7QU0AADX1p"
    },
    {
      "id": 870,
      "url": "EOTNRQSU0AApV3u"
    },
    {
      "id": 871,
      "url": "EOOLrGWVAAMc6RX"
    },
    {
      "id": 872,
      "url": "EOOLsP8U8AEYV0L"
    },
    {
      "id": 873,
      "url": "EOOLuA2U4AA8v8u"
    },
    {
      "id": 874,
      "url": "EOOLvYKUYAE9Mc3"
    },
    {
      "id": 875,
      "url": "ENsIJUVUcAUwiMW"
    },
    {
      "id": 876,
      "url": "ENr3TskUwAAvUS1"
    },
    {
      "id": 877,
      "url": "ENr3U6OUUAMhVkw"
    },
    {
      "id": 878,
      "url": "ENr3WL-UwAAcs_s"
    },
    {
      "id": 879,
      "url": "ENc0VdCUEAA9Kqu"
    },
    {
      "id": 880,
      "url": "ENc0WY1UwAIncFY"
    },
    {
      "id": 881,
      "url": "ENc0XKyVAAE87fA"
    },
    {
      "id": 882,
      "url": "EMtS-3WVAAMfO7Q"
    },
    {
      "id": 883,
      "url": "EMPQ5gxUcAEqo67"
    },
    {
      "id": 884,
      "url": "EMH5G3yUEAEKZoQ"
    },
    {
      "id": 885,
      "url": "EL36uSFU4AAdQqr"
    },
    {
      "id": 886,
      "url": "EL0146yU8AA-KhH"
    },
    {
      "id": 887,
      "url": "ELW4FNTVUAA2TPi"
    },
    {
      "id": 888,
      "url": "ELFTauLUYAE4HVk"
    },
    {
      "id": 889,
      "url": "ELFTdpbU0AAl4DT"
    },
    {
      "id": 890,
      "url": "ELAmObOU8AE-hyr"
    },
    {
      "id": 891,
      "url": "EHjnEUzUEAA2OHL"
    },
    {
      "id": 892,
      "url": "EHjnFtQU8AAxIWV"
    },
    {
      "id": 893,
      "url": "EHfBTQOUYAAd5Yy"
    },
    {
      "id": 894,
      "url": "EHeR76LUcAIPRO7"
    },
    {
      "id": 895,
      "url": "EGq8EpGVAAIFkxs"
    },
    {
      "id": 896,
      "url": "EGq8FwpU4AAkbE2"
    },
    {
      "id": 897,
      "url": "EGWwU0NVUAEr6UF"
    },
    {
      "id": 898,
      "url": "EGVFGz9UYAAnZ7X"
    },
    {
      "id": 899,
      "url": "EGVFIJsU8AAzj8B"
    },
    {
      "id": 900,
      "url": "EGRvWtaUYAAkcR5"
    },
    {
      "id": 901,
      "url": "EFYKeR_VAAAryJK"
    },
    {
      "id": 902,
      "url": "EE9s-P6U4AAa8yR"
    },
    {
      "id": 903,
      "url": "EE9s_v9VUAAUoGa"
    },
    {
      "id": 904,
      "url": "EE4MgRwU0AERy2q"
    },
    {
      "id": 905,
      "url": "EE2Sr60VUAAylzm"
    },
    {
      "id": 906,
      "url": "EEpoX9GU4AADpQC"
    },
    {
      "id": 907,
      "url": "EEkHr0kU4AEclkP"
    },
    {
      "id": 908,
      "url": "EEQhICBUYAEhhup"
    },
    {
      "id": 909,
      "url": "EEQhIo0VAAEoK30"
    },
    {
      "id": 910,
      "url": "EDm9cpCUEAAO2Hq"
    },
    {
      "id": 911,
      "url": "EDm9eKBUUAAkRdb"
    },
    {
      "id": 912,
      "url": "EDm9fW4UEAANnQd"
    },
    {
      "id": 913,
      "url": "EDi1TWPVUAA7dZA"
    },
    {
      "id": 914,
      "url": "EDi1WFNXsAAQ2zL"
    },
    {
      "id": 915,
      "url": "EDhLd5sU8AAi5pm"
    },
    {
      "id": 916,
      "url": "EDdNdoCU4AAMNPu"
    },
    {
      "id": 917,
      "url": "EDb0_LiVUAANJxk"
    },
    {
      "id": 918,
      "url": "EDbVJ3-UcAE_c9z"
    },
    {
      "id": 919,
      "url": "EDZBxnkUYAE1kUf"
    },
    {
      "id": 920,
      "url": "EA53G-DU4AEg0pv"
    },
    {
      "id": 921,
      "url": "EA3pmXyUIAAspwI"
    },
    {
      "id": 922,
      "url": "EAsoGG4UEAAmX3c"
    },
    {
      "id": 923,
      "url": "EAn0qgLU8AAcn2t"
    },
    {
      "id": 924,
      "url": "EAlYNi6U8AAcwjO"
    },
    {
      "id": 925,
      "url": "EAkBX_fUwAAQJD0"
    },
    {
      "id": 926,
      "url": "D_SeBdeU4AAEoad"
    },
    {
      "id": 927,
      "url": "D9PYpOfUEAA4Byi"
    },
    {
      "id": 928,
      "url": "D8MpDVrU8AAJRiS"
    }
  ]
}
